com/__init__.py
com/zuora/__init__.py
com/zuora/api_client.py
com/zuora/api_response.py
com/zuora/configuration.py
com/zuora/exceptions.py
com/zuora/py.typed
com/zuora/rest.py
com/zuora/api/__init__.py
com/zuora/api/accounting_codes_api.py
com/zuora/api/accounting_periods_api.py
com/zuora/api/accounts_api.py
com/zuora/api/actions_api.py
com/zuora/api/adjustments_api.py
com/zuora/api/aggregate_queries_api.py
com/zuora/api/api_health_api.py
com/zuora/api/attachments_api.py
com/zuora/api/bill_run_api.py
com/zuora/api/bill_run_health_api.py
com/zuora/api/billing_documents_api.py
com/zuora/api/billing_preview_run_api.py
com/zuora/api/booking_date_backfill_job_api.py
com/zuora/api/catalog_groups_api.py
com/zuora/api/configuration_templates_api.py
com/zuora/api/contact_snapshots_api.py
com/zuora/api/contacts_api.py
com/zuora/api/credit_memos_api.py
com/zuora/api/custom_event_triggers_api.py
com/zuora/api/custom_exchange_rates_api.py
com/zuora/api/custom_object_definitions_api.py
com/zuora/api/custom_object_jobs_api.py
com/zuora/api/custom_object_records_api.py
com/zuora/api/custom_payment_method_types_api.py
com/zuora/api/custom_scheduled_events_api.py
com/zuora/api/data_backfill_job_api.py
com/zuora/api/data_queries_api.py
com/zuora/api/debit_memos_api.py
com/zuora/api/describe_api.py
com/zuora/api/e_invoicing_api.py
com/zuora/api/electronic_payments_health_api.py
com/zuora/api/files_api.py
com/zuora/api/fulfillments_api.py
com/zuora/api/hosted_pages_api.py
com/zuora/api/imports_api.py
com/zuora/api/invoice_schedules_api.py
com/zuora/api/invoices_api.py
com/zuora/api/journal_runs_api.py
com/zuora/api/mass_updater_api.py
com/zuora/api/notifications_api.py
com/zuora/api/o_auth_api.py
com/zuora/api/operations_api.py
com/zuora/api/order_actions_api.py
com/zuora/api/order_line_items_api.py
com/zuora/api/orders_api.py
com/zuora/api/payment_authorization_api.py
com/zuora/api/payment_gateway_reconciliation_api.py
com/zuora/api/payment_gateways_api.py
jianfeng_py_test-1.1.353.2.dist-info/METADATA
jianfeng_py_test-1.1.353.2.dist-info/WHEEL
jianfeng_py_test-1.1.353.2.dist-info/top_level.txt
jianfeng_py_test-1.1.353.2.dist-info/RECORD
