Metadata-Version: 2.1
Name: jianfeng-py-test
Version: 1.1.353.2
Summary: Zuora API Reference
Home-page: 
Author: Zuora
Author-email: docs@zuora.com
License: MIT
Keywords: Zuora Python SDK
Requires-Dist: urllib3 (<2.1.0,>=1.25.3)
Requires-Dist: python-dateutil
Requires-Dist: pydantic (<2,>=1.10.5)
Requires-Dist: aenum
